mongotic/__init__.py
mongotic/exceptions.py
mongotic/model.py
mongotic/orm.py
mongotic/version.py
mongotic-0.2.0.dist-info/LICENSE
mongotic-0.2.0.dist-info/METADATA
mongotic-0.2.0.dist-info/WHEEL
mongotic-0.2.0.dist-info/RECORD
