Metadata-Version: 2.1
Name: mongotic
Version: 0.2.0
Summary: The concept of MongoDB, SQLAlchemy and Pydantic.
Home-page: https://github.com/dockhardman/mongotic
License: MIT
Keywords: mongodb,sqlalchemy,pydantic
Author: Allen Chou
Author-email: f1470891079@gmail.com
Requires-Python: >=3.7.0,<4.0.0
Classifier: License :: OSI Approved :: MIT License
Classifier: Programming Language :: Python :: 3
Classifier: Programming Language :: Python :: 3.7
Classifier: Programming Language :: Python :: 3.8
Classifier: Programming Language :: Python :: 3.9
Classifier: Programming Language :: Python :: 3.10
Classifier: Programming Language :: Python :: 3.11
Requires-Dist: pyassorted (>=0.7.5,<0.8.0)
Requires-Dist: pydantic (>=2,<3)
Requires-Dist: pymongo (>=4,<5)
Project-URL: Documentation, https://github.com/dockhardman/mongotic
Project-URL: Repository, https://github.com/dockhardman/mongotic
